README
setup.py
jump2/__init__.py
jump2/abtools/__init__.py
jump2/abtools/brillouin_zone.py
jump2/abtools/functional.py
jump2/abtools/globalvar.py
jump2/abtools/inputio.py
jump2/abtools/plot.py
jump2/abtools/diyflow/__init__.py
jump2/abtools/diyflow/miniflow.py
jump2/abtools/diyflow/mobility.py
jump2/abtools/diyflow/phonon.py
jump2/abtools/grep/__init__.py
jump2/abtools/grep/band.py
jump2/abtools/grep/dos.py
jump2/abtools/grep/example.py
jump2/abtools/grep/grep.py
jump2/abtools/grep/optic.py
jump2/abtools/grep/outcar.py
jump2/abtools/grep/xrays.py
jump2/abtools/pseudopotential/__init__.py
jump2/abtools/pseudopotential/potentials.py
jump2/abtools/vasp/__init__.py
jump2/abtools/vasp/check.py
jump2/abtools/vasp/correcting.py
jump2/abtools/vasp/errorkey.py
jump2/abtools/vasp/incar.py
jump2/abtools/vasp/kpoints.py
jump2/abtools/vasp/linear_T.py
jump2/abtools/vasp/monitor.py
jump2/abtools/vasp/phonon.py
jump2/abtools/vasp/potentials.py
jump2/abtools/vasp/setvasp.py
jump2/abtools/vasp/tasks.py
jump2/abtools/vasp/vaspflow.py
jump2/abtools/vasp/vaspio.py
jump2/abtools/vasp/vdw.py
jump2/analysis/__init__.py
jump2/analysis/analysis.py
jump2/compute/__cluster__.py
jump2/compute/__init__.py
jump2/compute/launch.py
jump2/compute/manager.py
jump2/compute/pool.py
jump2/compute/prepare.py
jump2/compute/single.py
jump2/compute/workflow.py
jump2/db/__init__.py
jump2/db/compute/__init__.py
jump2/db/compute/check.py
jump2/db/compute/job.py
jump2/db/compute/task.py
jump2/db/compute/testDB3.py
jump2/db/db/__init__.py
jump2/db/db/settings.py
jump2/db/db/urls.py
jump2/db/db/wsgi.py
jump2/db/iostream/__init__.py
jump2/db/iostream/cif.py
jump2/db/iostream/hall2hm.py
jump2/db/iostream/read.py
jump2/db/iostream/spaceGroupD3.py
jump2/db/iostream/write.py
jump2/db/manage/__init__.py
jump2/db/manage/pool.py
jump2/db/manage/submit.py
jump2/db/materials/__init__.py
jump2/db/materials/admin.py
jump2/db/materials/apps.py
jump2/db/materials/atom.py
jump2/db/materials/composition.py
jump2db.egg-info/PKG-INFO
jump2db.egg-info/SOURCES.txt
jump2db.egg-info/dependency_links.txt
jump2db.egg-info/top_level.txt
