Metadata-Version: 1.0
Name: jump2db
Version: 1.0
Summary: Python Package for HTP calculation.
Home-page: http://tdos.xyz
Author: Xin-Gang Zhao
Author-email: az351250965@gmail.com
License: Jilin University
Platform: UNKNOWN
